database_testing_tools/__init__.py
database_testing_tools/utils.py
database_testing_tools-1.0.5.dist-info/METADATA
database_testing_tools-1.0.5.dist-info/WHEEL
database_testing_tools-1.0.5.dist-info/RECORD
