Metadata-Version: 2.1
Name: database-testing-tools
Version: 1.0.5
Summary: A package to test our databases
Home-page: https://github.com/moj-analytical-services/database-testing-tools
Author: Thomas Hirsch
Author-email: thomas.hirsch@digital.justice.gov.uk
Requires-Python: >=3.8,<4
Classifier: Programming Language :: Python :: 3
Classifier: Programming Language :: Python :: 3.8
Classifier: Programming Language :: Python :: 3.9
Classifier: Programming Language :: Python :: 3.10
Classifier: Programming Language :: Python :: 3.11
Classifier: Programming Language :: Python :: 3.12
Classifier: Programming Language :: Python :: 3.13
Requires-Dist: altair (>=4.1,<5.0)
Requires-Dist: arrow-pd-parser (>=1.3.1)
Requires-Dist: dataengineeringutils3 (>=1.4,<2.0)
Requires-Dist: duckdb (>=0.8.0)
Requires-Dist: mojap-metadata (>=1.10.0,<2.0.0)
Requires-Dist: papermill (>=2.3.3,<3.0.0)
Requires-Dist: pydbtools (>=5.2,<6.0)
Requires-Dist: sqlglot (>=4.3.0,<5.0.0)
